O1tech/__init__.py
O1tech/db_connectors.py
O1tech/google_docs.py
O1tech/helpers.py
zero1tech/__init__.py
zero1tech/google_docs.py
O1tech-0.1.1.dist-info/METADATA
O1tech-0.1.1.dist-info/WHEEL
O1tech-0.1.1.dist-info/top_level.txt
O1tech-0.1.1.dist-info/RECORD
